dot_slash/__init__.py
dot_slash-1.0.0.dist-info/LICENSE
dot_slash-1.0.0.dist-info/METADATA
dot_slash-1.0.0.dist-info/WHEEL
dot_slash-1.0.0.dist-info/RECORD
