Metadata-Version: 2.1
Name: dot-slash
Version: 1.0.0
Summary: 
Author: Max Taggart
Author-email: taggart@digialdiagnostics.com
Requires-Python: >=3.10,<4.0
Classifier: Programming Language :: Python :: 3
Classifier: Programming Language :: Python :: 3.10
Classifier: Programming Language :: Python :: 3.11
Classifier: Programming Language :: Python :: 3.12
